sereal/__init__.py
sereal/sereal.py
sereal-0.1.0.dist-info/licenses/LICENSE
sereal-0.1.0.dist-info/METADATA
sereal-0.1.0.dist-info/WHEEL
sereal-0.1.0.dist-info/top_level.txt
sereal-0.1.0.dist-info/RECORD
