Metadata-Version: 2.4
Name: sereal
Version: 0.1.0
Summary: A lightweight serialization library
Author: 0880
License: Copyright 2025 0880880
Project-URL: Homepage, https://github.com/0880880/sereal
License-File: LICENSE
Dynamic: license-file
